spheronizator/__init__.py
spheronizator/config
spheronizator/functions.py
spheronizator/mol2parser.py
spheronizator/voxelBuilder.py
spheronizator/voxelize.py
spheronizator-0.1.1.dist-info/METADATA
spheronizator-0.1.1.dist-info/WHEEL
spheronizator-0.1.1.dist-info/entry_points.txt
spheronizator-0.1.1.dist-info/licenses/LICENSE
spheronizator-0.1.1.dist-info/RECORD
