Metadata-Version: 2.4
Name: spheronizator
Version: 0.1.1
Summary: spheronizator
License: BSD 3-Clause
License-File: LICENSE
Author: Matthew Richardson
Requires-Python: >=3.10
Classifier: License :: Other/Proprietary License
Classifier: Programming Language :: Python :: 3
Classifier: Programming Language :: Python :: 3.10
Classifier: Programming Language :: Python :: 3.11
Classifier: Programming Language :: Python :: 3.12
Classifier: Programming Language :: Python :: 3.13
Classifier: Programming Language :: Python :: 3.14
Requires-Dist: biopython (>=1.81,<1.86)
Requires-Dist: numpy (>=1.26.4,<2.0)
